pygizmo/__init__.py
pygizmo/example.py
pygizmo-0.1.1.dist-info/entry_points.txt
pygizmo-0.1.1.dist-info/LICENSE
pygizmo-0.1.1.dist-info/WHEEL
pygizmo-0.1.1.dist-info/METADATA
pygizmo-0.1.1.dist-info/RECORD
