Metadata-Version: 2.1
Name: pygizmo
Version: 0.1.1
Summary: Tools
Home-page: https://github.com/zpyoung/pygizmo
License: MIT
Author: Fabled Freedom
Author-email: zach@fabledfreedom.com
Requires-Python: >=3.8,<4.0
Classifier: Development Status :: 3 - Alpha
Classifier: Intended Audience :: Developers
Classifier: License :: OSI Approved :: MIT License
Classifier: Operating System :: OS Independent
Classifier: Programming Language :: Python :: 3
Classifier: Programming Language :: Python :: 3.10
Classifier: Programming Language :: Python :: 3.8
Classifier: Programming Language :: Python :: 3.9
Classifier: Topic :: Software Development :: Libraries :: Python Modules
Project-URL: Repository, https://github.com/zpyoung/pygizmo
